EmphysemaSeg/__init__.py
EmphysemaSeg/main.py
EmphysemaSeg/utils.py
EmphysemaSeg-0.1.0.dist-info/LICENSE.md
EmphysemaSeg-0.1.0.dist-info/METADATA
EmphysemaSeg-0.1.0.dist-info/WHEEL
EmphysemaSeg-0.1.0.dist-info/entry_points.txt
EmphysemaSeg-0.1.0.dist-info/top_level.txt
EmphysemaSeg-0.1.0.dist-info/RECORD
